proxy_db/__init__.py
proxy_db/_compat.py
proxy_db/cli.py
proxy_db/countries.py
proxy_db/db.py
proxy_db/exceptions.py
proxy_db/models.py
proxy_db/providers.py
proxy_db/proxies.py
proxy_db/utils.py
proxy_db/migrations/__init__.py
proxy_db/migrations/migration_0_3_0.py
proxy_db/migrations/migration_base.py
proxy_db-0.3.1.data/scripts/proxy-db
tests/__init__.py
tests/_compat.py
tests/test_countries.py
tests/test_migrations.py
tests/test_models.py
tests/test_providers.py
tests/test_proxies.py
tests/test_utils.py
proxy_db-0.3.1.dist-info/AUTHORS.rst
proxy_db-0.3.1.dist-info/LICENSE
proxy_db-0.3.1.dist-info/METADATA
proxy_db-0.3.1.dist-info/WHEEL
proxy_db-0.3.1.dist-info/top_level.txt
proxy_db-0.3.1.dist-info/RECORD
