Metadata-Version: 2.1
Name: proxy-db
Version: 0.3.1
Summary: Manage free and private proxies on local db for Python Projects.
Home-page: https://github.com/Nekmo/proxy-db/
Author: Nekmo
Author-email: contacto@nekmo.com
License: UNKNOWN
Download-URL: https://github.com/Nekmo/proxy-db/archive/master.zip
Keywords: proxy-db
Platform: linux
Classifier: License :: OSI Approved :: MIT License
Classifier: Programming Language :: Python :: 3.6
Classifier: Programming Language :: Python :: 3.5
Classifier: Programming Language :: Python :: 3.7
Classifier: Programming Language :: Python :: 2.7
Classifier: Programming Language :: Python :: 3.4
Classifier: Operating System :: POSIX
Classifier: Operating System :: POSIX :: Linux
Classifier: Natural Language :: English
Classifier: Development Status :: 5 - Production/Stable
Provides: tests
Provides: proxy_db
Provides-Extra: geoip
